packagedata.py
packagedata-1.1.0.dist-info/licenses/LICENSE
packagedata-1.1.0.dist-info/METADATA
packagedata-1.1.0.dist-info/WHEEL
packagedata-1.1.0.dist-info/top_level.txt
packagedata-1.1.0.dist-info/RECORD
