Metadata-Version: 2.4
Name: packagedata
Version: 1.1.0
Summary: A custom pkg_resources to importlib.resources/metadata migration helper.
Author-email: "KuraLabs S.R.L" <info@kuralabs.io>
License: Apache-2.0
Classifier: Development Status :: 5 - Production/Stable
Classifier: Intended Audience :: Developers
Classifier: Natural Language :: English
Classifier: Operating System :: POSIX :: Linux
Classifier: Programming Language :: Python :: 3
Classifier: Programming Language :: Python :: 3.8
Classifier: Programming Language :: Python :: 3.9
Classifier: Programming Language :: Python :: 3.10
Classifier: Programming Language :: Python :: 3.11
Classifier: Programming Language :: Python :: 3.12
Classifier: Programming Language :: Python :: 3.13
Classifier: Programming Language :: Python :: 3.14
Requires-Python: >=3.8
License-File: LICENSE
Requires-Dist: importlib-resources; python_version < "3.9"
Requires-Dist: importlib-metadata; python_version < "3.9"
Dynamic: license-file
